HISTORY.md
LICENSE
README.md
setup.cfg
setup.py
winsrv/__init__.py
winsrv/abcs.py
winsrv/service.py
winsrv/util.py
winsrv.egg-info/PKG-INFO
winsrv.egg-info/SOURCES.txt
winsrv.egg-info/dependency_links.txt
winsrv.egg-info/not-zip-safe
winsrv.egg-info/requires.txt
winsrv.egg-info/top_level.txt
winsrv/tests/__init__.py
winsrv/tests/fixtures.py
winsrv/tests/test_services.py
winsrv/tests/util.py