Metadata-Version: 1.1
Name: winsrv
Version: 1.9
Summary: Easy Windows Service creation and management
Home-page: UNKNOWN
Author: Petri Savolainen
Author-email: petri.savolainen@koodaamo.fi
License: GPL
Platform: UNKNOWN
Classifier: Operating System :: Microsoft :: Windows
Classifier: Environment :: Win32 (MS Windows)
Classifier: Programming Language :: Python :: 3.5
Classifier: Programming Language :: Python :: 3
Classifier: Programming Language :: Python :: 3 :: Only
